{
  "_class": "shapePath",
  "booleanOperation": 1,
  "clippingMaskMode": 0,
  "do_objectID": "E1FA3BA6-4B73-4A23-9F32-794AE0D19719",
  "edited": true,
  "exportOptions": {
    "_class": "exportOptions",
    "do_objectID": "921D730D-6060-4949-B55A-B6D5F073301C",
    "exportFormats": [
    ],
    "includedLayerIds": [
    ],
    "layerOptions": 0,
    "shouldTrim": false
  },
  "frame": {
    "_class": "rect",
    "constrainProportions": false,
    "do_objectID": "81BB6FED-323F-4B56-9E13-2D4E1B3CBF1F",
    "height": 13.00000000000047,
    "width": 13.00000000000047,
    "x": 2.000000000000073,
    "y": 2.000000000000073
  },
  "hasClippingMask": false,
  "isClosed": true,
  "isFixedToViewport": false,
  "isFlippedHorizontal": false,
  "isFlippedVertical": false,
  "isLocked": false,
  "isVisible": true,
  "layerListExpandedType": 0,
  "name": "Combined Shape",
  "nameIsFixed": false,
  "pointRadiusBehaviour": 1,
  "points": [
    {
      "_class": "curvePoint",
      "cornerRadius": 0,
      "curveFrom": "{0.77614237489763127, 1}",
      "curveMode": 2,
      "curveTo": "{0.22385762510236873, 1}",
      "hasCurveFrom": true,
      "hasCurveTo": true,
      "point": "{0.5, 1}"
    },
    {
      "_class": "curvePoint",
      "cornerRadius": 0,
      "curveFrom": "{1, 0.22385762510236873}",
      "curveMode": 2,
      "curveTo": "{1, 0.77614237489763127}",
      "hasCurveFrom": true,
      "hasCurveTo": true,
      "point": "{1, 0.5}"
    },
    {
      "_class": "curvePoint",
      "cornerRadius": 0,
      "curveFrom": "{0.22385762510236873, 0}",
      "curveMode": 2,
      "curveTo": "{0.77614237489763127, 0}",
      "hasCurveFrom": true,
      "hasCurveTo": true,
      "point": "{0.5, 0}"
    },
    {
      "_class": "curvePoint",
      "cornerRadius": 0,
      "curveFrom": "{0, 0.77614237489763127}",
      "curveMode": 2,
      "curveTo": "{0, 0.22385762510236873}",
      "hasCurveFrom": true,
      "hasCurveTo": true,
      "point": "{0, 0.5}"
    }
  ],
  "resizingConstraint": 63,
  "resizingType": 0,
  "rotation": 0,
  "shouldBreakMaskChain": false,
  "style": {
    "_class": "style",
    "do_objectID": "8F8EBE97-EDF1-447D-B3A5-AA4119A120A2",
    "endMarkerType": 0,
    "fills": [
      {
        "_class": "fill",
        "color": {
          "_class": "color",
          "alpha": 1,
          "blue": 0,
          "green": 0,
          "red": 0
        },
        "fillType": 0,
        "isEnabled": true,
        "noiseIndex": 0,
        "noiseIntensity": 0,
        "patternFillType": 1,
        "patternTileScale": 1
      }
    ],
    "miterLimit": 10,
    "startMarkerType": 0,
    "windingRule": 0
  }
}