{
  "_class": "shapePath",
  "booleanOperation": -1,
  "clippingMaskMode": 0,
  "do_objectID": "AF26A0A8-9CBB-4CAF-ABDF-DED232266EBB",
  "edited": true,
  "exportOptions": {
    "_class": "exportOptions",
    "do_objectID": "B9F7378B-E4D4-4492-832F-92330FA4AD64",
    "exportFormats": [
    ],
    "includedLayerIds": [
    ],
    "layerOptions": 0,
    "shouldTrim": false
  },
  "frame": {
    "_class": "rect",
    "constrainProportions": false,
    "do_objectID": "6904379C-AB97-4030-A5F9-839D1E5B2DF6",
    "height": 2.75142857142857,
    "width": 1.071428571428571,
    "x": 6.666596019981666,
    "y": 3.677142857142855
  },
  "hasClippingMask": false,
  "isClosed": true,
  "isFixedToViewport": false,
  "isFlippedHorizontal": false,
  "isFlippedVertical": false,
  "isLocked": false,
  "isVisible": true,
  "layerListExpandedType": 0,
  "name": "Path",
  "nameIsFixed": false,
  "pointRadiusBehaviour": 1,
  "points": [
    {
      "_class": "curvePoint",
      "cornerRadius": 0,
      "curveFrom": "{0.21600000000000019, 1}",
      "curveMode": 1,
      "curveTo": "{0.21600000000000019, 1}",
      "hasCurveFrom": false,
      "hasCurveTo": false,
      "point": "{0.21600000000000019, 1}"
    },
    {
      "_class": "curvePoint",
      "cornerRadius": 0,
      "curveFrom": "{0.78399999999999981, 1}",
      "curveMode": 1,
      "curveTo": "{0.78399999999999981, 1}",
      "hasCurveFrom": false,
      "hasCurveTo": false,
      "point": "{0.78399999999999981, 1}"
    },
    {
      "_class": "curvePoint",
      "cornerRadius": 0,
      "curveFrom": "{0.78399999999999981, 0}",
      "curveMode": 1,
      "curveTo": "{0.78399999999999981, 0}",
      "hasCurveFrom": false,
      "hasCurveTo": false,
      "point": "{0.78399999999999981, 0}"
    },
    {
      "_class": "curvePoint",
      "cornerRadius": 0,
      "curveFrom": "{0.21600000000000019, 0}",
      "curveMode": 1,
      "curveTo": "{0.21600000000000019, 0}",
      "hasCurveFrom": false,
      "hasCurveTo": false,
      "point": "{0.21600000000000019, 0}"
    }
  ],
  "resizingConstraint": 63,
  "resizingType": 0,
  "rotation": 0,
  "shouldBreakMaskChain": false,
  "style": {
    "_class": "style",
    "do_objectID": "663593F5-0115-4A51-A2B8-79FE7B926D69",
    "endMarkerType": 0,
    "miterLimit": 10,
    "startMarkerType": 0,
    "windingRule": 1
  }
}