{
  "_class": "group",
  "booleanOperation": -1,
  "clippingMaskMode": 0,
  "do_objectID": "B5BF6983-5258-4766-816E-E4ACD340D6CF",
  "exportOptions": {
    "_class": "exportOptions",
    "do_objectID": "E975B4FD-60F8-4FB4-92CA-9D7F1F6B9B78",
    "exportFormats": [
    ],
    "includedLayerIds": [
    ],
    "layerOptions": 0,
    "shouldTrim": false
  },
  "frame": {
    "_class": "rect",
    "constrainProportions": false,
    "do_objectID": "1CAB1315-C307-42E6-9950-3AA849D86126",
    "height": 129,
    "width": 98,
    "x": 276,
    "y": 45
  },
  "groupLayout": {
    "_class": "MSImmutableFreeformGroupLayout"
  },
  "hasClickThrough": false,
  "hasClippingMask": false,
  "isFixedToViewport": false,
  "isFlippedHorizontal": false,
  "isFlippedVertical": false,
  "isLocked": false,
  "isVisible": true,
  "layerListExpandedType": 2,
  "layers": [
    {
      "class": "text",
      "id": "7F6217BD-5BA6-46AA-9D67-0A9D324D69C2"
    },
    {
      "class": "group",
      "id": "D6B43406-E72F-447A-BC0F-6B6F67449D6C"
    }
  ],
  "name": "Group 2",
  "nameIsFixed": false,
  "resizingConstraint": 63,
  "resizingType": 0,
  "rotation": 0,
  "shouldBreakMaskChain": false,
  "style": {
    "_class": "style",
    "do_objectID": "B3CA25E2-7E9A-4059-8B08-C028F31923E0",
    "endMarkerType": 0,
    "miterLimit": 10,
    "startMarkerType": 0,
    "windingRule": 1
  }
}